LICENSE
MANIFEST.in
README.rst
setup.cfg
setup.py
filecho/__init__.py
filecho/__main__.py
filecho/cli.py
filecho/server.py
filecho/version.py
filecho.egg-info/PKG-INFO
filecho.egg-info/SOURCES.txt
filecho.egg-info/dependency_links.txt
filecho.egg-info/entry_points.txt
filecho.egg-info/not-zip-safe
filecho.egg-info/requires.txt
filecho.egg-info/top_level.txt