Metadata-Version: 1.1
Name: filecho
Version: 0.1.4
Summary: A web server for serving static files
Home-page: https://github.com/jadbin/filecho
Author: jadbin.com
Author-email: jadbin.com@hotmail.com
License: Apache 2
Platform: UNKNOWN
Classifier: License :: OSI Approved :: Apache Software License
Classifier: Intended Audience :: Developers
Classifier: Programming Language :: Python
Classifier: Programming Language :: Python :: 3
Classifier: Programming Language :: Python :: 3.5
Classifier: Topic :: Internet :: WWW/HTTP
